{
    "name": "Integrate",
    "thumb": "/media/uploads/archive/integrate.webp",
    "url": "",
    "wayback_url": "https://web.archive.org/web/20210703022958/https://www.integrate.com/",
    "years": "~2019",
    "services": [
        "Development"
    ],
    "era": "studio",
    "blurb_md": "Authored a custom WordPress theme and a stack of page templates for Integrate, via Studio Science — production front-end at scale. Retired when the marketing site was rebuilt around 2023; preserved here via the Wayback Machine.",
    "sort_order": 3,
    "status": "published"
}
